setup.cfg
setup.py
pyblockchain/__init__.py
python_blockchain_api.egg-info/PKG-INFO
python_blockchain_api.egg-info/SOURCES.txt
python_blockchain_api.egg-info/dependency_links.txt
python_blockchain_api.egg-info/requires.txt
python_blockchain_api.egg-info/top_level.txt
python_blockchain_api.egg-info/zip-safe