Metadata-Version: 1.1
Name: python-blockchain-api
Version: 0.0.2
Summary: Python API for interacting with blockchain.info.
Home-page: https://github.com/nkgilley/python-blockchain-api
Author: Nolan Gilley
Author-email: nkgilley@gmail.com
License: MIT
Download-URL: https://github.com/nkgilley/python-blockchain-api/archive/0.0.1.tar.gz
Platform: UNKNOWN
